README.md
setup.py
fan_courier_client/__init__.py
fan_courier_client/addresses.py
fan_courier_client/awb.py
fan_courier_client/client.py
fan_courier_client/common.py
fan_courier_client/constants.py
fan_courier_client/decorators.py
fan_courier_client/fan_curier.py
fan_courier_client/orders.py
fan_courier_client/rates.py
fan_courier_client/remarks.py
fan_courier_client/services.py
fan_courier_client/sheets.py
fan_courier_client/transfers.py
fan_courier_client/utils.py
fan_courier_client.egg-info/PKG-INFO
fan_courier_client.egg-info/SOURCES.txt
fan_courier_client.egg-info/dependency_links.txt
fan_courier_client.egg-info/not-zip-safe
fan_courier_client.egg-info/requires.txt
fan_courier_client.egg-info/top_level.txt