Metadata-Version: 2.1
Name: fan-courier-client
Version: 0.2
Summary: Fan Courier Python API Client Library
Home-page: https://github.com/RodiZaharadji/fan-courier-client
Author: EBS Integrator
Author-email: office@ebs-integrator.com
License: MIT
Platform: UNKNOWN
Classifier: Development Status :: 5 - Production/Stable
Classifier: Intended Audience :: Developers
Classifier: Operating System :: OS Independent
Classifier: Programming Language :: Python
Classifier: Programming Language :: Python :: 3.6
Classifier: Programming Language :: Python :: 3.7
Classifier: Programming Language :: Python :: 3.8
Classifier: Programming Language :: Python :: 3.9
Classifier: Topic :: Utilities
Requires-Python: >=3.4
